[[{"t": "\n", "lp": -2.8322055, "olp": -3.1464658}, {"t": "Today", "lp": -6.3400183, "olp": -6.7206845}], [{"t": "EC", "lp": -9.944466, "olp": -9.921176}, {"t": "The", "lp": -3.1384096, "olp": -3.1360197}], [{"t": "3", "lp": -6.213398, "olp": -5.522134}, {"t": " number", "lp": -1.6852753, "olp": -2.5651026}], [{"t": "\n\n", "lp": -3.1230521, "olp": -2.9469578}, {"t": " Certified", "lp": -9.984847, "olp": -10.959531}], [{"t": "+", "lp": -8.479708, "olp": -9.611055}, {"t": "Posted", "lp": -6.107916, "olp": -5.8212566}], [{"t": "231", "lp": -8.727369, "olp": -12.4992285}, {"t": "104", "lp": -8.379175, "olp": -9.344083}], [{"t": "/-", "lp": -3.5069857, "olp": -5.361682}, {"t": "\n\n", "lp": -1.0084031, "olp": -0.3624095}], [{"t": "67", "lp": -6.0374517, "olp": -6.2954435}, {"t": "107", "lp": -5.4457607, "olp": -6.127475}], [{"t": "\n\n", "lp": -0.002141459, "olp": -0.40304342}, {"t": "\n\n", "lp": -0.0021308719, "olp": -0.40342572}], [{"t": "Posts", "lp": -0.010600169, "olp": -1.2962041}, {"t": "Posts", "lp": -0.010919896, "olp": -1.2962041}], [{"t": ":", "lp": -1.7120534e-05, "olp": -0.0051586893}, {"t": ":", "lp": -1.7120534e-05, "olp": -0.0051586893}], [{"t": " ", "lp": -3.1782583e-05, "olp": -0.011155226}, {"t": " ", "lp": -3.1782583e-05, "olp": -0.011155226}], [{"t": "658", "lp": -7.530973, "olp": -7.7878127}, {"t": "349", "lp": -6.335758, "olp": -7.108125}], [{"t": "1", "lp": -2.6216311, "olp": -3.0116553}, {"t": "0", "lp": -2.564826, "olp": -3.0507178}], [{"t": "\n\n", "lp": -0.00022034443, "olp": -0.059029303}, {"t": "\n\n", "lp": -0.00021402664, "olp": -0.059029303}], [{"t": "+", "lp": -0.16204952, "olp": -3.9413903}, {"t": "+", "lp": -0.16467969, "olp": -3.9413903}], [{"t": "231", "lp": -0.00051717076, "olp": -0.28635144}, {"t": "231", "lp": -0.00050835335, "olp": -0.28635144}], [{"t": "/-", "lp": -4.246537e-06, "olp": -0.00077401253}, {"t": "/-", "lp": -4.246537e-06, "olp": -0.0007861603}], [{"t": "67", "lp": -0.00047094907, "olp": -0.0039551556}, {"t": "67", "lp": -0.00047297185, "olp": -0.0039551556}], [{"t": "Posts", "lp": -0.0012229667, "olp": -0.005493903}, {"t": "Posts", "lp": -0.0011487908, "olp": -0.005493903}], [{"t": ":", "lp": -4.3202e-07, "olp": -0.00070218404}, {"t": ":", "lp": -4.3202e-07, "olp": -0.00070242246}], [{"t": " ", "lp": -6.4325184e-05, "olp": -0.004271427}, {"t": " ", "lp": -6.3609965e-05, "olp": -0.004271427}], [{"t": "658", "lp": -3.106736e-05, "olp": -0.0005456458}, {"t": "658", "lp": -3.094816e-05, "olp": -0.0005456458}], [{"t": "1", "lp": -1.7432603e-06, "olp": -0.0024134691}, {"t": "1", "lp": -1.6240566e-06, "olp": -0.0024134691}], [{"t": " Re", "lp": -0.49973372, "olp": -1.0667833}, {"t": " what", "lp": -9.15913, "olp": -9.404674}], [{"t": ":", "lp": -0.00012142374, "olp": -0.0057825474}, {"t": ":", "lp": -0.000121542944, "olp": -0.0057825474}], [{"t": " Name", "lp": -7.675131, "olp": -8.087029}, {"t": " Hearts", "lp": -8.301128, "olp": -10.98742}], [{"t": " never", "lp": -12.455654, "olp": -10.011698}, {"t": " change", "lp": -2.6300519, "olp": -3.1806912}], [{"t": " repeated", "lp": -5.804824, "olp": -6.388973}, {"t": "-ending", "lp": -4.880041, "olp": -6.498348}], [{"t": " \u00ab", "lp": -1.9838642, "olp": -1.483014}, {"t": " in", "lp": -1.2338803, "olp": -2.467389}], [{"t": " Reply", "lp": -0.011784536, "olp": -0.10185086}, {"t": " Reply", "lp": -0.011966427, "olp": -0.10185086}], [{"t": " #", "lp": -3.2929079e-06, "olp": -0.00014180024}, {"t": " #", "lp": -3.2929079e-06, "olp": -0.00014180024}], [{"t": "15", "lp": -1.1335615, "olp": -1.6828855}, {"t": "30", "lp": -2.1637793, "olp": -2.3703856}], [{"t": " on", "lp": -3.9411618e-05, "olp": -0.004950882}, {"t": " on", "lp": -3.9411618e-05, "olp": -0.004950882}], [{"t": ":", "lp": -6.2729996e-06, "olp": -8.017927e-05}, {"t": ":", "lp": -6.2729996e-06, "olp": -8.12521e-05}], [{"t": " Friday", "lp": -1.9958087, "olp": -5.7624774}, {"t": " Tuesday", "lp": -1.8369354, "olp": -5.6687274}], [{"t": ",", "lp": -5.5122365e-07, "olp": -0.5094113}, {"t": ",", "lp": -5.5122365e-07, "olp": -0.5094113}], [{"t": " June", "lp": -2.405867, "olp": -2.4860554}, {"t": " February", "lp": -2.3699508, "olp": -2.6657429}], [{"t": " ", "lp": -9.014684e-06, "olp": -0.035334524}, {"t": " ", "lp": -9.133887e-06, "olp": -0.035334524}], [{"t": "26", "lp": -3.2534478, "olp": -3.3375409}, {"t": "2", "lp": -3.1241145, "olp": -5.8687906}], [{"t": ",", "lp": -1.8074163e-05, "olp": -0.06492032}, {"t": ",", "lp": -1.7597347e-05, "olp": -0.06492032}], [{"t": " ", "lp": -2.4584822e-06, "olp": -0.0007373235}, {"t": " ", "lp": -2.4584822e-06, "olp": -0.0007373235}], [{"t": "202", "lp": -0.77498317, "olp": -2.0929537}, {"t": "200", "lp": -1.7069043, "olp": -0.74920356}], [{"t": "0", "lp": -1.2829201e-05, "olp": -0.09402207}, {"t": "0", "lp": -1.2590794e-05, "olp": -0.09402207}], [{"t": ",", "lp": -2.577686e-06, "olp": -0.019131519}, {"t": ",", "lp": -2.577686e-06, "olp": -0.019131519}], [{"t": " ", "lp": 0.0, "olp": -0.0021376517}, {"t": " ", "lp": 0.0, "olp": -0.0021376517}], [{"t": "06", "lp": -4.5987015, "olp": -3.054441}, {"t": "08", "lp": -3.102458, "olp": -2.820066}], [{"t": ":", "lp": -2.1008714e-06, "olp": -7.1238996e-05}, {"t": ":", "lp": -2.1008714e-06, "olp": -7.064298e-05}], [{"t": "21", "lp": -4.101679, "olp": -4.137356}, {"t": "33", "lp": -4.0719786, "olp": -4.106106}], [{"t": ":", "lp": -1.3306016e-05, "olp": -0.039429013}, {"t": ":", "lp": -1.3306016e-05, "olp": -0.039429013}], [{"t": "06", "lp": -4.1522813, "olp": -4.115102}, {"t": "34", "lp": -4.114815, "olp": -4.0231895}], [{"t": " \u00bb", "lp": -0.007076583, "olp": -2.9243383}, {"t": " \u00bb", "lp": -0.007073625, "olp": -2.9243383}], [{"t": " Rock", "lp": -10.2646475, "olp": -9.396672}, {"t": " Quote", "lp": -0.94891196, "olp": -0.8947194}], [{"t": "in", "lp": -3.6102781, "olp": -2.9899404}, {"t": " &", "lp": -5.093381, "olp": -5.4975986}], [{"t": " Rod", "lp": -7.031603, "olp": -6.0874195}, {"t": ".", "lp": -6.251135, "olp": -4.8413258}], [{"t": "ders", "lp": -2.8852034, "olp": -4.6605315}, {"t": "\n\n", "lp": -3.072774, "olp": -2.1956878}], [{"t": " and", "lp": -3.2883482, "olp": -3.58775}, {"t": ",", "lp": -2.5466318, "olp": -2.7830625}], [{"t": " jeep", "lp": -13.195278, "olp": -11.197394}, {"t": " The", "lp": -3.8018193, "olp": -4.0805464}], [{"t": "\n\n", "lp": -5.4691916, "olp": -6.0953145}, {"t": "ers", "lp": -0.3940711, "olp": -1.243752}], [{"t": "S", "lp": -4.595815, "olp": -4.8586035}, {"t": "Kill", "lp": -9.993083, "olp": -9.753135}], [{"t": "imp", "lp": -4.184233, "olp": -5.7553816}, {"t": "ala", "lp": -8.063016, "olp": -8.532725}], [{"t": "sons", "lp": -1.3722968, "olp": -2.0443802}, {"t": "sons", "lp": -1.376544, "olp": -2.0443802}], [{"t": " Rose", "lp": -10.305504, "olp": -11.08981}, {"t": "\n\n", "lp": -2.1714528, "olp": -1.2856113}], [{"t": " family", "lp": -5.303833, "olp": -5.963745}, {"t": " and", "lp": -1.6187711, "olp": -3.2723389}], [{"t": " reunion", "lp": -7.0150166, "olp": -7.979594}, {"t": " \u00ab", "lp": -4.9502764, "olp": -5.710063}], [{"t": " (", "lp": -3.5113778, "olp": -4.682073}, {"t": " pet", "lp": -10.108616, "olp": -10.143988}], [{"t": "they", "lp": -5.260539, "olp": -4.9813523}, {"t": "on", "lp": -5.9633436, "olp": -6.3943996}], [{"t": "\u2019ll", "lp": -7.209836, "olp": -7.420446}, {"t": " have", "lp": -2.4553723, "olp": -2.4438834}], [{"t": " kill", "lp": -4.610489, "olp": -5.116345}, {"t": " think", "lp": -5.0479913, "olp": -5.8624387}], [{"t": " me", "lp": -1.1447599, "olp": -1.4563665}, {"t": " each", "lp": -2.8628726, "olp": -2.8001165}], [{"t": " now", "lp": -5.3609977, "olp": -3.9332192}, {"t": ")\n\n", "lp": -2.2671547, "olp": -2.1832192}], [{"t": ")", "lp": -1.2158637, "olp": -1.5472796}, {"t": ")", "lp": -1.2159972, "olp": -1.5471087}], [{"t": " Logged", "lp": -0.45089418, "olp": -1.0227008}, {"t": " \u00bb", "lp": -6.725373, "olp": -5.8156695}], [{"t": "\n\n", "lp": -0.36202404, "olp": -0.79002076}, {"t": " Book", "lp": -9.885733, "olp": -9.519372}], [{"t": "S", "lp": -4.169362, "olp": -4.0268726}, {"t": "Re", "lp": -2.194434, "olp": -1.4174974}], [{"t": ".A", "lp": -6.173011, "olp": -7.8394465}, {"t": "apper", "lp": -8.241765, "olp": -7.6454735}], [{"t": ".F", "lp": -2.8948317, "olp": -2.9248767}, {"t": ".M", "lp": -0.7330469, "olp": -1.8780017}], [{"t": ".C", "lp": -0.15978031, "olp": -6.167412}, {"t": ".C", "lp": -0.15578313, "olp": -6.167412}], [{"t": ".\n\n", "lp": -0.9025294, "olp": -0.77228755}, {"t": ".\n\n", "lp": -0.9144289, "olp": -0.77228755}], [{"t": "+", "lp": -0.08615593, "olp": -0.22974433}, {"t": "+", "lp": -0.08076219, "olp": -0.22974433}], [{"t": "19", "lp": -4.680772, "olp": -6.03504}, {"t": "27", "lp": -4.8211193, "olp": -5.6372647}], [{"t": "/-", "lp": -2.0219828e-05, "olp": -0.014661834}, {"t": "/-", "lp": -1.7954959e-05, "olp": -0.014661834}], [{"t": "13", "lp": -3.7236369, "olp": -3.9440427}, {"t": "4", "lp": -3.502345, "olp": -3.8392975}], [{"t": "\n\n", "lp": -9.186123e-05, "olp": -0.007336369}, {"t": "\n\n", "lp": -8.947716e-05, "olp": -0.007336369}], [{"t": "Posts", "lp": -0.03281199, "olp": -0.038519923}, {"t": "Posts", "lp": -0.032775775, "olp": -0.038519923}], [{"t": ":", "lp": -2.1008714e-06, "olp": -0.00071648485}, {"t": ":", "lp": -2.1008714e-06, "olp": -0.00071648485}], [{"t": " ", "lp": -3.8219583e-05, "olp": -0.0010002978}, {"t": " ", "lp": -3.619312e-05, "olp": -0.0010002978}], [{"t": "355", "lp": -6.7765985, "olp": -6.6118026}, {"t": "284", "lp": -6.5469522, "olp": -6.3461776}], [{"t": "\n\n", "lp": -1.4098263, "olp": -1.4828161}, {"t": "\n\n", "lp": -1.4261081, "olp": -1.4828161}], [{"t": "+", "lp": -0.07120126, "olp": -0.39935142}, {"t": "+", "lp": -0.06936481, "olp": -0.39935142}], [{"t": "19", "lp": -0.00012284685, "olp": -0.0018486744}, {"t": "19", "lp": -0.00011915887, "olp": -0.0018486744}], [{"t": "/-", "lp": -5.9914648e-05, "olp": -9.4914985e-06}, {"t": "/-", "lp": -5.8841815e-05, "olp": -9.4914985e-06}], [{"t": "13", "lp": -0.00021271907, "olp": -0.001046624}, {"t": "13", "lp": -0.00020961977, "olp": -0.001046624}], [{"t": "Posts", "lp": -0.0001341712, "olp": -0.00015324011}, {"t": "Posts", "lp": -0.00013512482, "olp": -0.00015097891}], [{"t": ":", "lp": -3.1737043e-06, "olp": -5.2643223e-05}, {"t": ":", "lp": -3.1737043e-06, "olp": -5.347765e-05}], [{"t": " ", "lp": -6.730528e-05, "olp": -3.917321e-05}, {"t": " ", "lp": -6.682846e-05, "olp": -3.917321e-05}], [{"t": "355", "lp": -1.3067608e-05, "olp": -4.9424725e-05}, {"t": "355", "lp": -1.3067608e-05, "olp": -4.9424725e-05}], [{"t": " Re", "lp": -0.017092768, "olp": -0.028316345}, {"t": " Re", "lp": -0.017145269, "olp": -0.028303487}], [{"t": ":", "lp": -4.3202e-07, "olp": -4.5133394e-05}, {"t": ":", "lp": -4.3202e-07, "olp": -4.5133394e-05}], [{"t": " Name", "lp": -0.0019392271, "olp": -0.0029425172}, {"t": " Name", "lp": -0.0019111462, "olp": -0.0029425172}]]